{"cameraMode":{"drawMode":0,"name":"Shaded","section":"Shading Mode"},"sceneLighting":true,"audioPlay":false,"sceneViewState":{"showFog":true,"showMaterialUpdate":false,"showSkybox":true,"showFlares":true,"showImageEffects":true,"showParticleSystems":true,"showVisualEffectGraphs":true,"m_FxEnabled":true},"in2DMode":false,"pivot":{"x":6.649803638458252,"y":-4.2616472244262699,"z":-0.6205081939697266},"rotation":{"x":0.36523059010505679,"y":0.24551834166049958,"z":-0.10048963874578476,"w":0.8923230171203613},"size":10.42081069946289,"orthographic":false}